tm_merger/__init__.py
tm_merger/modules/__init__.py
tm_merger/modules/tm_merger.py
tm_merger-0.0.3.dist-info/METADATA
tm_merger-0.0.3.dist-info/WHEEL
tm_merger-0.0.3.dist-info/top_level.txt
tm_merger-0.0.3.dist-info/RECORD
