Metadata-Version: 2.1
Name: tm-merger
Version: 0.0.3
Summary: Ansible module for base and tenant config merger.
Home-page: https://github.com/lvrfrc87/tm_merger
Author: Federico Olivieri
Author-email: federico.olivieri@ticketmaster.nl
License: UNKNOWN
Platform: UNKNOWN
Classifier: Topic :: Utilities
Classifier: Programming Language :: Python :: 3
Classifier: Programming Language :: Python :: 3.5
Classifier: Programming Language :: Python :: 3.6
Classifier: Programming Language :: Python :: 3.7
Classifier: Operating System :: POSIX :: Linux
Classifier: Operating System :: MacOS
Requires-Dist: more-itertools
